{"name": "zhaoml529/dubbo-common-parent", "id": 74420491, "created_at": "2016-11-22 01:08:32", "watchers_count": 9, "stargazers_count": 9, "forks_count": 5, "updated_at": "2018-10-17 05:25:03", "pushed_at": "2018-10-17 05:25:02", "fetched_at": "2019-10-10 21:58:01", "files": ["dubbo-common-config/pom.xml", "dubbo-common-core/pom.xml", "dubbo-common-web/pom.xml", "dubbo-common/pom.xml", "dubbo-facade-activiti/pom.xml", "dubbo-facade-base/pom.xml", "dubbo-facade-deliver/pom.xml", "dubbo-facade-log/pom.xml", "dubbo-facade-user/pom.xml", "dubbo-service-activiti/pom.xml", "dubbo-service-base/pom.xml", "dubbo-service-deliver/pom.xml", "dubbo-service-log/pom.xml", "dubbo-service-user/pom.xml", "dubbo-web-base/pom.xml", "dubbo-web-html/pom.xml", "pom.xml"]}