{"name": "justlive1/oxygen", "id": 150673713, "created_at": "2018-09-28 02:19:57", "watchers_count": 99, "stargazers_count": 99, "forks_count": 8, "updated_at": "2019-09-30 02:53:36", "pushed_at": "2019-10-02 00:57:43", "fetched_at": "2019-10-10 09:04:06", "files": ["oxygen-aop/pom.xml", "oxygen-cache/pom.xml", "oxygen-core/pom.xml", "oxygen-ioc/pom.xml", "oxygen-jdbc/pom.xml", "oxygen-job/pom.xml", "oxygen-web-jetty/pom.xml", "oxygen-web-tomcat/pom.xml", "oxygen-web-undertow/pom.xml", "oxygen-web/pom.xml", "pom.xml"]}