{"name": "mongodb/stitch-android-sdk", "id": 87100729, "created_at": "2017-04-03 17:19:42", "watchers_count": 48, "stargazers_count": 48, "forks_count": 25, "updated_at": "2019-10-09 18:31:04", "pushed_at": "2019-10-09 18:31:00", "fetched_at": "2019-10-10 17:57:49", "files": ["config/checkstyle.xml", "android/examples/snippets/build.gradle", "android/sdk/build.gradle", "core/services/aws-s3/build.gradle", "core/services/aws-ses/build.gradle", "core/services/aws/build.gradle", "core/services/fcm/build.gradle", "core/services/http/build.gradle", "core/services/mongodb-local/build.gradle", "core/services/twilio/build.gradle", "core/testutils/build.gradle", "server/core/build.gradle", "server/sdk/build.gradle", "server/services/aws-s3/build.gradle", "server/services/aws-ses/build.gradle", "server/services/aws/build.gradle", "server/services/fcm/build.gradle", "server/services/http/build.gradle", "server/services/twilio/build.gradle", "android/build.gradle", "core/admin-client/build.gradle", "core/sdk/build.gradle", "server/coretest/build.gradle", "android/services/mongodb-remote-perftests/build.gradle", "server/testutils/build.gradle", "android/core/build.gradle", "android/coretest/build.gradle", "android/examples/fcm/build.gradle", "android/examples/stress-tests/build.gradle", "android/examples/todo-sync/build.gradle", "android/examples/todo/build.gradle", "android/services/aws-s3/build.gradle", "android/services/aws-ses/build.gradle", "android/services/aws/build.gradle", "android/services/fcm/build.gradle", "android/services/http/build.gradle", "android/services/mongodb-local/build.gradle", "android/services/mongodb-remote/build.gradle", "android/services/twilio/build.gradle", "android/testutils/build.gradle", "build.gradle", "core/services/mongodb-remote/build.gradle", "server/services/mongodb-remote/build.gradle", "config/checkstyle-exclude.xml", "config/checkstyle-intellij.xml"]}