{"name": "bugsnag/bugsnag-java", "id": 8467178, "created_at": "2013-02-27 22:39:47", "watchers_count": 45, "stargazers_count": 45, "forks_count": 27, "updated_at": "2019-08-16 13:14:18", "pushed_at": "2019-08-16 13:14:19", "fetched_at": "2019-10-10 18:24:01", "files": ["config/checkstyle/checkstyle.xml", "examples/spring-web/build.gradle", "examples/spring/build.gradle", "features/fixtures/mazerunner/build.gradle", "features/fixtures/mazerunnerspringboot/build.gradle", "features/fixtures/mazerunnerplainspring/build.gradle", "features/fixtures/scenarios/build.gradle", "bugsnag-spring/build.gradle", "build.gradle", "examples/logback/build.gradle", "examples/servlet/build.gradle", "examples/simple/build.gradle", "bugsnag/build.gradle", ".travis.yml"]}