{
    "project_name": "apache-ignite-3",
    "error_id": "16",
    "information": {
        "errors": [
            {
                "line": "24",
                "column": "5",
                "severity": "error",
                "message": "'VARIABLE_DEF' should be separated from previous line.",
                "source": "com.puppycrawl.tools.checkstyle.checks.whitespace.EmptyLineSeparatorCheck"
            }
        ]
    },
    "source_code": "public class CliOptions extends RpcOptions {\n    private int timeoutMs;\n    private int maxRetry;\n\n    public int getTimeoutMs() {\n        return this.timeoutMs;",
    "results": [
        {
            "tool": "styler",
            "errors": [],
            "diff": "diff --git a/home/fernanda/mnt/fernanda/git-styler/styler/python/experiments/results/apache-ignite-3/errored/1/16/CliOptions.java b/home/fernanda/mnt/fernanda/git-styler/styler/python/experiments/results/apache-ignite-3/styler/16/CliOptions.java\nindex 66c67766fa0..5d4282f5482 100644\n--- a/home/fernanda/mnt/fernanda/git-styler/styler/python/experiments/results/apache-ignite-3/errored/1/16/CliOptions.java\n+++ b/home/fernanda/mnt/fernanda/git-styler/styler/python/experiments/results/apache-ignite-3/styler/16/CliOptions.java\n@@ -21,6 +21,7 @@ package org.apache.ignite.raft.jraft.option;\n  */\n public class CliOptions extends RpcOptions {\n     private int timeoutMs;\n+\n     private int maxRetry;\n \n     public int getTimeoutMs() {\n",
            "diff_size": 1
        },
        {
            "tool": "intellij",
            "errors": [],
            "diff": "diff --git a/home/fernanda/mnt/fernanda/git-styler/styler/python/experiments/results/apache-ignite-3/errored/1/16/CliOptions.java b/home/fernanda/mnt/fernanda/git-styler/styler/python/experiments/results/apache-ignite-3/intellij/16/CliOptions.java\nindex 66c67766fa0..6f646ec9a1d 100644\n--- a/home/fernanda/mnt/fernanda/git-styler/styler/python/experiments/results/apache-ignite-3/errored/1/16/CliOptions.java\n+++ b/home/fernanda/mnt/fernanda/git-styler/styler/python/experiments/results/apache-ignite-3/intellij/16/CliOptions.java\n@@ -14,28 +14,30 @@\n  * See the License for the specific language governing permissions and\n  * limitations under the License.\n  */\n+\n package org.apache.ignite.raft.jraft.option;\n \n /**\n  * Cli service options.\n  */\n public class CliOptions extends RpcOptions {\n-    private int timeoutMs;\n-    private int maxRetry;\n+  private int timeoutMs;\n+\n+  private int maxRetry;\n \n-    public int getTimeoutMs() {\n-        return this.timeoutMs;\n-    }\n+  public int getTimeoutMs() {\n+    return this.timeoutMs;\n+  }\n \n-    public void setTimeoutMs(int timeoutMs) {\n-        this.timeoutMs = timeoutMs;\n-    }\n+  public void setTimeoutMs(int timeoutMs) {\n+    this.timeoutMs = timeoutMs;\n+  }\n \n-    public int getMaxRetry() {\n-        return this.maxRetry;\n-    }\n+  public int getMaxRetry() {\n+    return this.maxRetry;\n+  }\n \n-    public void setMaxRetry(int maxRetry) {\n-        this.maxRetry = maxRetry;\n-    }\n+  public void setMaxRetry(int maxRetry) {\n+    this.maxRetry = maxRetry;\n+  }\n }\n",
            "diff_size": 16
        },
        {
            "tool": "naturalize",
            "errors": [
                {
                    "line": "24",
                    "column": "5",
                    "severity": "error",
                    "message": "'VARIABLE_DEF' should be separated from previous line.",
                    "source": "com.puppycrawl.tools.checkstyle.checks.whitespace.EmptyLineSeparatorCheck"
                }
            ],
            "diff": "diff --git a/home/fernanda/mnt/fernanda/git-styler/styler/python/experiments/results/apache-ignite-3/errored/1/16/CliOptions.java b/home/fernanda/mnt/fernanda/git-styler/styler/python/experiments/results/apache-ignite-3/naturalize/16/CliOptions.java\nindex 66c67766fa0..0a6197db02f 100644\n--- a/home/fernanda/mnt/fernanda/git-styler/styler/python/experiments/results/apache-ignite-3/errored/1/16/CliOptions.java\n+++ b/home/fernanda/mnt/fernanda/git-styler/styler/python/experiments/results/apache-ignite-3/naturalize/16/CliOptions.java\n@@ -38,4 +38,4 @@ public class CliOptions extends RpcOptions {\n     public void setMaxRetry(int maxRetry) {\n         this.maxRetry = maxRetry;\n     }\n-}\n+}\n\\ No newline at end of file\n",
            "diff_size": 1
        },
        {
            "tool": "codebuff",
            "errors": [
                {
                    "line": "24",
                    "column": "1",
                    "severity": "error",
                    "message": "'CLASS_DEF' has more than 1 empty lines before.",
                    "source": "com.puppycrawl.tools.checkstyle.checks.whitespace.EmptyLineSeparatorCheck"
                },
                {
                    "line": "29",
                    "column": "5",
                    "severity": "error",
                    "message": "'VARIABLE_DEF' has more than 1 empty lines before.",
                    "source": "com.puppycrawl.tools.checkstyle.checks.whitespace.EmptyLineSeparatorCheck"
                },
                {
                    "line": "32",
                    "column": "5",
                    "severity": "error",
                    "message": "'METHOD_DEF' has more than 1 empty lines before.",
                    "source": "com.puppycrawl.tools.checkstyle.checks.whitespace.EmptyLineSeparatorCheck"
                }
            ],
            "diff": "diff --git a/home/fernanda/mnt/fernanda/git-styler/styler/python/experiments/results/apache-ignite-3/errored/1/16/CliOptions.java b/home/fernanda/mnt/fernanda/git-styler/styler/python/experiments/results/apache-ignite-3/codebuff/16/CliOptions.java\nindex 66c67766fa0..08009030e61 100644\n--- a/home/fernanda/mnt/fernanda/git-styler/styler/python/experiments/results/apache-ignite-3/errored/1/16/CliOptions.java\n+++ b/home/fernanda/mnt/fernanda/git-styler/styler/python/experiments/results/apache-ignite-3/codebuff/16/CliOptions.java\n@@ -19,10 +19,16 @@ package org.apache.ignite.raft.jraft.option;\n /**\n  * Cli service options.\n  */\n+\n+\n public class CliOptions extends RpcOptions {\n+\n     private int timeoutMs;\n+\n+\n     private int maxRetry;\n \n+\n     public int getTimeoutMs() {\n         return this.timeoutMs;\n     }\n@@ -38,4 +44,4 @@ public class CliOptions extends RpcOptions {\n     public void setMaxRetry(int maxRetry) {\n         this.maxRetry = maxRetry;\n     }\n-}\n+}\n\\ No newline at end of file\n",
            "diff_size": 7
        },
        {
            "tool": "styler_random",
            "errors": [],
            "diff": "diff --git a/home/fernanda/mnt/fernanda/git-styler/styler/python/experiments/results/apache-ignite-3/errored/1/16/CliOptions.java b/home/fernanda/mnt/fernanda/git-styler/styler/python/experiments/results/apache-ignite-3/styler_random/16/CliOptions.java\nindex 66c67766fa0..5d4282f5482 100644\n--- a/home/fernanda/mnt/fernanda/git-styler/styler/python/experiments/results/apache-ignite-3/errored/1/16/CliOptions.java\n+++ b/home/fernanda/mnt/fernanda/git-styler/styler/python/experiments/results/apache-ignite-3/styler_random/16/CliOptions.java\n@@ -21,6 +21,7 @@ package org.apache.ignite.raft.jraft.option;\n  */\n public class CliOptions extends RpcOptions {\n     private int timeoutMs;\n+\n     private int maxRetry;\n \n     public int getTimeoutMs() {\n",
            "diff_size": 1
        },
        {
            "tool": "styler_three_grams",
            "errors": [],
            "diff": "diff --git a/home/fernanda/mnt/fernanda/git-styler/styler/python/experiments/results/apache-ignite-3/errored/1/16/CliOptions.java b/home/fernanda/mnt/fernanda/git-styler/styler/python/experiments/results/apache-ignite-3/styler_three_grams/16/CliOptions.java\nindex 66c67766fa0..5d4282f5482 100644\n--- a/home/fernanda/mnt/fernanda/git-styler/styler/python/experiments/results/apache-ignite-3/errored/1/16/CliOptions.java\n+++ b/home/fernanda/mnt/fernanda/git-styler/styler/python/experiments/results/apache-ignite-3/styler_three_grams/16/CliOptions.java\n@@ -21,6 +21,7 @@ package org.apache.ignite.raft.jraft.option;\n  */\n public class CliOptions extends RpcOptions {\n     private int timeoutMs;\n+\n     private int maxRetry;\n \n     public int getTimeoutMs() {\n",
            "diff_size": 1
        }
    ],
    "repaired_by": [
        "styler",
        "intellij",
        "styler_random",
        "styler_three_grams"
    ],
    "not_repaired_by": [
        "naturalize",
        "codebuff"
    ]
}