{
    "project_name": "graphfoundation-ongdb",
    "error_id": "490",
    "information": {
        "errors": [
            {
                "line": "1",
                "severity": "error",
                "message": "Missing, wrong or duplicated license header",
                "source": "com.puppycrawl.tools.checkstyle.checks.regexp.RegexpSinglelineCheck"
            }
        ]
    },
    "source_code": "/*\n * Copyright (c) 2002-2018 \"Neo Technology,\"\n * Network Engine for Objects in Lund AB [http://neotechnology.com]\n *",
    "results": [
        {
            "tool": "styler",
            "errors": [
                {
                    "line": "1",
                    "severity": "error",
                    "message": "Missing, wrong or duplicated license header",
                    "source": "com.puppycrawl.tools.checkstyle.checks.regexp.RegexpSinglelineCheck"
                }
            ],
            "diff": "",
            "diff_size": 0
        },
        {
            "tool": "intellij",
            "errors": [
                {
                    "line": "1",
                    "severity": "error",
                    "message": "Missing, wrong or duplicated license header",
                    "source": "com.puppycrawl.tools.checkstyle.checks.regexp.RegexpSinglelineCheck"
                },
                {
                    "line": "31",
                    "column": "48",
                    "severity": "error",
                    "message": "'(' is not followed by whitespace.",
                    "source": "com.puppycrawl.tools.checkstyle.checks.whitespace.ParenPadCheck"
                },
                {
                    "line": "31",
                    "column": "58",
                    "severity": "error",
                    "message": "')' is not preceded with whitespace.",
                    "source": "com.puppycrawl.tools.checkstyle.checks.whitespace.ParenPadCheck"
                },
                {
                    "line": "35",
                    "column": "63",
                    "severity": "error",
                    "message": "'(' is not followed by whitespace.",
                    "source": "com.puppycrawl.tools.checkstyle.checks.whitespace.ParenPadCheck"
                },
                {
                    "line": "35",
                    "column": "103",
                    "severity": "error",
                    "message": "')' is not preceded with whitespace.",
                    "source": "com.puppycrawl.tools.checkstyle.checks.whitespace.ParenPadCheck"
                },
                {
                    "line": "37",
                    "column": "57",
                    "severity": "error",
                    "message": "'(' is not followed by whitespace.",
                    "source": "com.puppycrawl.tools.checkstyle.checks.whitespace.ParenPadCheck"
                },
                {
                    "line": "37",
                    "column": "73",
                    "severity": "error",
                    "message": "')' is not preceded with whitespace.",
                    "source": "com.puppycrawl.tools.checkstyle.checks.whitespace.ParenPadCheck"
                },
                {
                    "line": "39",
                    "column": "61",
                    "severity": "error",
                    "message": "'(' is not followed by whitespace.",
                    "source": "com.puppycrawl.tools.checkstyle.checks.whitespace.ParenPadCheck"
                },
                {
                    "line": "39",
                    "column": "77",
                    "severity": "error",
                    "message": "')' is not preceded with whitespace.",
                    "source": "com.puppycrawl.tools.checkstyle.checks.whitespace.ParenPadCheck"
                },
                {
                    "line": "41",
                    "column": "57",
                    "severity": "error",
                    "message": "'(' is not followed by whitespace.",
                    "source": "com.puppycrawl.tools.checkstyle.checks.whitespace.ParenPadCheck"
                },
                {
                    "line": "41",
                    "column": "85",
                    "severity": "error",
                    "message": "')' is not preceded with whitespace.",
                    "source": "com.puppycrawl.tools.checkstyle.checks.whitespace.ParenPadCheck"
                },
                {
                    "line": "50",
                    "column": "57",
                    "severity": "error",
                    "message": "'(' is not followed by whitespace.",
                    "source": "com.puppycrawl.tools.checkstyle.checks.whitespace.ParenPadCheck"
                },
                {
                    "line": "50",
                    "column": "67",
                    "severity": "error",
                    "message": "')' is not preceded with whitespace.",
                    "source": "com.puppycrawl.tools.checkstyle.checks.whitespace.ParenPadCheck"
                },
                {
                    "line": "62",
                    "column": "66",
                    "severity": "error",
                    "message": "'(' is not followed by whitespace.",
                    "source": "com.puppycrawl.tools.checkstyle.checks.whitespace.ParenPadCheck"
                },
                {
                    "line": "62",
                    "column": "82",
                    "severity": "error",
                    "message": "')' is not preceded with whitespace.",
                    "source": "com.puppycrawl.tools.checkstyle.checks.whitespace.ParenPadCheck"
                },
                {
                    "line": "68",
                    "column": "70",
                    "severity": "error",
                    "message": "'(' is not followed by whitespace.",
                    "source": "com.puppycrawl.tools.checkstyle.checks.whitespace.ParenPadCheck"
                },
                {
                    "line": "68",
                    "column": "86",
                    "severity": "error",
                    "message": "')' is not preceded with whitespace.",
                    "source": "com.puppycrawl.tools.checkstyle.checks.whitespace.ParenPadCheck"
                },
                {
                    "line": "74",
                    "column": "72",
                    "severity": "error",
                    "message": "'(' is not followed by whitespace.",
                    "source": "com.puppycrawl.tools.checkstyle.checks.whitespace.ParenPadCheck"
                },
                {
                    "line": "74",
                    "column": "112",
                    "severity": "error",
                    "message": "')' is not preceded with whitespace.",
                    "source": "com.puppycrawl.tools.checkstyle.checks.whitespace.ParenPadCheck"
                },
                {
                    "line": "80",
                    "column": "66",
                    "severity": "error",
                    "message": "'(' is not followed by whitespace.",
                    "source": "com.puppycrawl.tools.checkstyle.checks.whitespace.ParenPadCheck"
                },
                {
                    "line": "80",
                    "column": "84",
                    "severity": "error",
                    "message": "')' is not preceded with whitespace.",
                    "source": "com.puppycrawl.tools.checkstyle.checks.whitespace.ParenPadCheck"
                }
            ],
            "diff": "diff --git a/home/fernanda/mnt/fernanda/git-styler/styler/python/experiments/results/graphfoundation-ongdb/errored/1/490/RaftMembershipStateMachineEventHandler.java b/home/fernanda/mnt/fernanda/git-styler/styler/python/experiments/results/graphfoundation-ongdb/intellij/490/RaftMembershipStateMachineEventHandler.java\nindex 91216fc663e..3cabc5381ab 100644\n--- a/home/fernanda/mnt/fernanda/git-styler/styler/python/experiments/results/graphfoundation-ongdb/errored/1/490/RaftMembershipStateMachineEventHandler.java\n+++ b/home/fernanda/mnt/fernanda/git-styler/styler/python/experiments/results/graphfoundation-ongdb/intellij/490/RaftMembershipStateMachineEventHandler.java\n@@ -17,6 +17,7 @@\n  * You should have received a copy of the GNU Affero General Public License\n  * along with this program. If not, see <http://www.gnu.org/licenses/>.\n  */\n+\n package org.neo4j.causalclustering.core.consensus.membership;\n \n import java.util.Set;\n@@ -27,64 +28,68 @@ import org.neo4j.causalclustering.identity.MemberId;\n \n interface RaftMembershipStateMachineEventHandler\n {\n-    RaftMembershipStateMachineEventHandler onRole( Role role );\n+  RaftMembershipStateMachineEventHandler onRole(Role role);\n+\n+  RaftMembershipStateMachineEventHandler onRaftGroupCommitted();\n+\n+  RaftMembershipStateMachineEventHandler onFollowerStateChange(FollowerStates<MemberId> followerStates);\n+\n+  RaftMembershipStateMachineEventHandler onMissingMember(MemberId member);\n+\n+  RaftMembershipStateMachineEventHandler onSuperfluousMember(MemberId member);\n+\n+  RaftMembershipStateMachineEventHandler onTargetChanged(Set<MemberId> targetMembers);\n \n-    RaftMembershipStateMachineEventHandler onRaftGroupCommitted();\n+  void onExit();\n \n-    RaftMembershipStateMachineEventHandler onFollowerStateChange( FollowerStates<MemberId> followerStates );\n+  void onEntry();\n+\n+  abstract class Adapter implements RaftMembershipStateMachineEventHandler\n+  {\n+    @Override\n+    public RaftMembershipStateMachineEventHandler onRole(Role role)\n+    {\n+      return this;\n+    }\n+\n+    @Override\n+    public RaftMembershipStateMachineEventHandler onRaftGroupCommitted()\n+    {\n+      return this;\n+    }\n \n-    RaftMembershipStateMachineEventHandler onMissingMember( MemberId member );\n+    @Override\n+    public RaftMembershipStateMachineEventHandler onMissingMember(MemberId member)\n+    {\n+      return this;\n+    }\n \n-    RaftMembershipStateMachineEventHandler onSuperfluousMember( MemberId member );\n+    @Override\n+    public RaftMembershipStateMachineEventHandler onSuperfluousMember(MemberId member)\n+    {\n+      return this;\n+    }\n \n-    RaftMembershipStateMachineEventHandler onTargetChanged( Set<MemberId> targetMembers );\n+    @Override\n+    public RaftMembershipStateMachineEventHandler onFollowerStateChange(FollowerStates<MemberId> followerStates)\n+    {\n+      return this;\n+    }\n \n-    void onExit();\n+    @Override\n+    public RaftMembershipStateMachineEventHandler onTargetChanged(Set targetMembers)\n+    {\n+      return this;\n+    }\n \n-    void onEntry();\n+    @Override\n+    public void onExit()\n+    {\n+    }\n \n-    abstract class Adapter implements RaftMembershipStateMachineEventHandler\n+    @Override\n+    public void onEntry()\n     {\n-        @Override\n-        public RaftMembershipStateMachineEventHandler onRole( Role role )\n-        {\n-            return this;\n-        }\n-\n-        @Override\n-        public RaftMembershipStateMachineEventHandler onRaftGroupCommitted()\n-        {\n-            return this;\n-        }\n-\n-        @Override\n-        public RaftMembershipStateMachineEventHandler onMissingMember( MemberId member )\n-        {\n-            return this;\n-        }\n-\n-        @Override\n-        public RaftMembershipStateMachineEventHandler onSuperfluousMember( MemberId member )\n-        {\n-            return this;\n-        }\n-\n-        @Override\n-        public RaftMembershipStateMachineEventHandler onFollowerStateChange( FollowerStates<MemberId> followerStates )\n-        {\n-            return this;\n-        }\n-\n-        @Override\n-        public RaftMembershipStateMachineEventHandler onTargetChanged( Set targetMembers )\n-        {\n-            return this;\n-        }\n-\n-        @Override\n-        public void onExit() {}\n-\n-        @Override\n-        public void onEntry() {}\n     }\n+  }\n }\n",
            "diff_size": 96
        },
        {
            "tool": "naturalize",
            "errors": [
                {
                    "line": "1",
                    "severity": "error",
                    "message": "Missing, wrong or duplicated license header",
                    "source": "com.puppycrawl.tools.checkstyle.checks.regexp.RegexpSinglelineCheck"
                }
            ],
            "diff": "diff --git a/home/fernanda/mnt/fernanda/git-styler/styler/python/experiments/results/graphfoundation-ongdb/errored/1/490/RaftMembershipStateMachineEventHandler.java b/home/fernanda/mnt/fernanda/git-styler/styler/python/experiments/results/graphfoundation-ongdb/naturalize/490/RaftMembershipStateMachineEventHandler.java\nindex 91216fc663e..c3216671258 100644\n--- a/home/fernanda/mnt/fernanda/git-styler/styler/python/experiments/results/graphfoundation-ongdb/errored/1/490/RaftMembershipStateMachineEventHandler.java\n+++ b/home/fernanda/mnt/fernanda/git-styler/styler/python/experiments/results/graphfoundation-ongdb/naturalize/490/RaftMembershipStateMachineEventHandler.java\n@@ -28,16 +28,12 @@ import org.neo4j.causalclustering.identity.MemberId;\n interface RaftMembershipStateMachineEventHandler\n {\n     RaftMembershipStateMachineEventHandler onRole( Role role );\n-\n-    RaftMembershipStateMachineEventHandler onRaftGroupCommitted();\n+RaftMembershipStateMachineEventHandler onRaftGroupCommitted();\n \n     RaftMembershipStateMachineEventHandler onFollowerStateChange( FollowerStates<MemberId> followerStates );\n-\n-    RaftMembershipStateMachineEventHandler onMissingMember( MemberId member );\n-\n-    RaftMembershipStateMachineEventHandler onSuperfluousMember( MemberId member );\n-\n-    RaftMembershipStateMachineEventHandler onTargetChanged( Set<MemberId> targetMembers );\n+RaftMembershipStateMachineEventHandler onMissingMember( MemberId member );\n+RaftMembershipStateMachineEventHandler onSuperfluousMember( MemberId member );\n+RaftMembershipStateMachineEventHandler onTargetChanged( Set<MemberId> targetMembers );\n \n     void onExit();\n \n@@ -82,9 +78,13 @@ interface RaftMembershipStateMachineEventHandler\n         }\n \n         @Override\n-        public void onExit() {}\n+        public void onExit()\n+{\n+}\n \n         @Override\n-        public void onEntry() {}\n-    }\n+        public void onEntry()\n+{\n }\n+    }\n+}\n\\ No newline at end of file\n",
            "diff_size": 15
        },
        {
            "tool": "codebuff",
            "errors": null,
            "diff": null
        },
        {
            "tool": "styler_random",
            "errors": [
                {
                    "line": "1",
                    "severity": "error",
                    "message": "Missing, wrong or duplicated license header",
                    "source": "com.puppycrawl.tools.checkstyle.checks.regexp.RegexpSinglelineCheck"
                }
            ],
            "diff": "",
            "diff_size": 0
        },
        {
            "tool": "styler_three_grams",
            "errors": [
                {
                    "line": "1",
                    "severity": "error",
                    "message": "Missing, wrong or duplicated license header",
                    "source": "com.puppycrawl.tools.checkstyle.checks.regexp.RegexpSinglelineCheck"
                }
            ],
            "diff": "",
            "diff_size": 0
        }
    ],
    "repaired_by": [],
    "not_repaired_by": [
        "styler",
        "intellij",
        "naturalize",
        "codebuff",
        "styler_random",
        "styler_three_grams"
    ]
}