{
    "project_name": "neo4j-neo4j",
    "error_id": "1876",
    "information": {
        "errors": [
            {
                "line": "1",
                "severity": "error",
                "message": "Missing, wrong or duplicated license header",
                "source": "com.puppycrawl.tools.checkstyle.checks.regexp.RegexpSinglelineCheck"
            }
        ]
    },
    "source_code": "/*\n * Copyright (c) 2002-2020 \"Neo4j,\"\n * Neo4j Sweden AB [http://neo4j.com]\n *",
    "results": [
        {
            "tool": "styler",
            "errors": [
                {
                    "line": "1",
                    "severity": "error",
                    "message": "Missing, wrong or duplicated license header",
                    "source": "com.puppycrawl.tools.checkstyle.checks.regexp.RegexpSinglelineCheck"
                }
            ],
            "diff": "",
            "diff_size": 0
        },
        {
            "tool": "intellij",
            "errors": [
                {
                    "line": "1",
                    "severity": "error",
                    "message": "Missing, wrong or duplicated license header",
                    "source": "com.puppycrawl.tools.checkstyle.checks.regexp.RegexpSinglelineCheck"
                },
                {
                    "line": "38",
                    "column": "40",
                    "severity": "error",
                    "message": "'(' is not followed by whitespace.",
                    "source": "com.puppycrawl.tools.checkstyle.checks.whitespace.ParenPadCheck"
                },
                {
                    "line": "42",
                    "column": "61",
                    "severity": "error",
                    "message": "')' is not preceded with whitespace.",
                    "source": "com.puppycrawl.tools.checkstyle.checks.whitespace.ParenPadCheck"
                },
                {
                    "line": "44",
                    "column": "14",
                    "severity": "error",
                    "message": "'(' is not followed by whitespace.",
                    "source": "com.puppycrawl.tools.checkstyle.checks.whitespace.ParenPadCheck"
                },
                {
                    "line": "44",
                    "column": "28",
                    "severity": "error",
                    "message": "')' is not preceded with whitespace.",
                    "source": "com.puppycrawl.tools.checkstyle.checks.whitespace.ParenPadCheck"
                },
                {
                    "line": "59",
                    "column": "15",
                    "severity": "error",
                    "message": "'(' is not followed by whitespace.",
                    "source": "com.puppycrawl.tools.checkstyle.checks.whitespace.ParenPadCheck"
                },
                {
                    "line": "59",
                    "column": "53",
                    "severity": "error",
                    "message": "')' is not preceded with whitespace.",
                    "source": "com.puppycrawl.tools.checkstyle.checks.whitespace.ParenPadCheck"
                },
                {
                    "line": "61",
                    "column": "12",
                    "severity": "error",
                    "message": "'(' is not followed by whitespace.",
                    "source": "com.puppycrawl.tools.checkstyle.checks.whitespace.ParenPadCheck"
                },
                {
                    "line": "61",
                    "column": "20",
                    "severity": "error",
                    "message": "')' is not preceded with whitespace.",
                    "source": "com.puppycrawl.tools.checkstyle.checks.whitespace.ParenPadCheck"
                },
                {
                    "line": "64",
                    "column": "9",
                    "severity": "error",
                    "message": "'}' at column 9 should be alone on a line.",
                    "source": "com.puppycrawl.tools.checkstyle.checks.blocks.RightCurlyCheck"
                },
                {
                    "line": "81",
                    "column": "12",
                    "severity": "error",
                    "message": "'(' is not followed by whitespace.",
                    "source": "com.puppycrawl.tools.checkstyle.checks.whitespace.ParenPadCheck"
                },
                {
                    "line": "81",
                    "column": "32",
                    "severity": "error",
                    "message": "')' is not preceded with whitespace.",
                    "source": "com.puppycrawl.tools.checkstyle.checks.whitespace.ParenPadCheck"
                },
                {
                    "line": "84",
                    "column": "19",
                    "severity": "error",
                    "message": "'(' is not followed by whitespace.",
                    "source": "com.puppycrawl.tools.checkstyle.checks.whitespace.ParenPadCheck"
                },
                {
                    "line": "84",
                    "column": "41",
                    "severity": "error",
                    "message": "')' is not preceded with whitespace.",
                    "source": "com.puppycrawl.tools.checkstyle.checks.whitespace.ParenPadCheck"
                },
                {
                    "line": "86",
                    "column": "21",
                    "severity": "error",
                    "message": "'(' is not followed by whitespace.",
                    "source": "com.puppycrawl.tools.checkstyle.checks.whitespace.ParenPadCheck"
                },
                {
                    "line": "86",
                    "column": "48",
                    "severity": "error",
                    "message": "')' is not preceded with whitespace.",
                    "source": "com.puppycrawl.tools.checkstyle.checks.whitespace.ParenPadCheck"
                },
                {
                    "line": "88",
                    "column": "24",
                    "severity": "error",
                    "message": "'(' is not followed by whitespace.",
                    "source": "com.puppycrawl.tools.checkstyle.checks.whitespace.ParenPadCheck"
                },
                {
                    "line": "88",
                    "column": "78",
                    "severity": "error",
                    "message": "')' is not preceded with whitespace.",
                    "source": "com.puppycrawl.tools.checkstyle.checks.whitespace.ParenPadCheck"
                },
                {
                    "line": "90",
                    "column": "28",
                    "severity": "error",
                    "message": "'(' is not followed by whitespace.",
                    "source": "com.puppycrawl.tools.checkstyle.checks.whitespace.ParenPadCheck"
                },
                {
                    "line": "90",
                    "column": "65",
                    "severity": "error",
                    "message": "')' is not preceded with whitespace.",
                    "source": "com.puppycrawl.tools.checkstyle.checks.whitespace.ParenPadCheck"
                },
                {
                    "line": "93",
                    "column": "32",
                    "severity": "error",
                    "message": "'(' is not followed by whitespace.",
                    "source": "com.puppycrawl.tools.checkstyle.checks.whitespace.ParenPadCheck"
                },
                {
                    "line": "93",
                    "column": "49",
                    "severity": "error",
                    "message": "')' is not preceded with whitespace.",
                    "source": "com.puppycrawl.tools.checkstyle.checks.whitespace.ParenPadCheck"
                },
                {
                    "line": "97",
                    "column": "25",
                    "severity": "error",
                    "message": "'}' at column 25 should be alone on a line.",
                    "source": "com.puppycrawl.tools.checkstyle.checks.blocks.RightCurlyCheck"
                },
                {
                    "line": "108",
                    "column": "44",
                    "severity": "error",
                    "message": "'(' is not followed by whitespace.",
                    "source": "com.puppycrawl.tools.checkstyle.checks.whitespace.ParenPadCheck"
                },
                {
                    "line": "108",
                    "column": "64",
                    "severity": "error",
                    "message": "')' is not preceded with whitespace.",
                    "source": "com.puppycrawl.tools.checkstyle.checks.whitespace.ParenPadCheck"
                },
                {
                    "line": "110",
                    "column": "41",
                    "severity": "error",
                    "message": "'(' is not followed by whitespace.",
                    "source": "com.puppycrawl.tools.checkstyle.checks.whitespace.ParenPadCheck"
                },
                {
                    "line": "110",
                    "column": "71",
                    "severity": "error",
                    "message": "')' is not preceded with whitespace.",
                    "source": "com.puppycrawl.tools.checkstyle.checks.whitespace.ParenPadCheck"
                },
                {
                    "line": "112",
                    "column": "39",
                    "severity": "error",
                    "message": "'(' is not followed by whitespace.",
                    "source": "com.puppycrawl.tools.checkstyle.checks.whitespace.ParenPadCheck"
                },
                {
                    "line": "112",
                    "column": "97",
                    "severity": "error",
                    "message": "')' is not preceded with whitespace.",
                    "source": "com.puppycrawl.tools.checkstyle.checks.whitespace.ParenPadCheck"
                }
            ],
            "diff": "diff --git a/home/fernanda/mnt/fernanda/git-styler/styler/python/experiments/results/neo4j-neo4j/errored/1/1876/PropertyFilteringIterator.java b/home/fernanda/mnt/fernanda/git-styler/styler/python/experiments/results/neo4j-neo4j/intellij/1876/PropertyFilteringIterator.java\nindex 4285f38603e..334bded836d 100644\n--- a/home/fernanda/mnt/fernanda/git-styler/styler/python/experiments/results/neo4j-neo4j/errored/1/1876/PropertyFilteringIterator.java\n+++ b/home/fernanda/mnt/fernanda/git-styler/styler/python/experiments/results/neo4j-neo4j/intellij/1876/PropertyFilteringIterator.java\n@@ -27,7 +27,7 @@ import org.neo4j.internal.kernel.api.PropertyCursor;\n import org.neo4j.io.IOUtils;\n \n public abstract class PropertyFilteringIterator<T extends Entity, TOKEN_CURSOR extends Cursor, ENTITY_CURSOR extends Cursor>\n-        extends PrefetchingEntityResourceIterator<T>\n+  extends PrefetchingEntityResourceIterator<T>\n {\n \n     private final TOKEN_CURSOR entityTokenCursor;\n@@ -35,13 +35,13 @@ public abstract class PropertyFilteringIterator<T extends Entity, TOKEN_CURSOR e\n     private final PropertyCursor propertyCursor;\n     private final IndexQuery[] queries;\n \n-    protected PropertyFilteringIterator( TOKEN_CURSOR entityTokenCursor,\n-                                         ENTITY_CURSOR entityCursor,\n-                                         PropertyCursor propertyCursor,\n-                                         EntityFactory<T> entityFactory,\n-                                         IndexQuery[] queries )\n+    protected PropertyFilteringIterator(TOKEN_CURSOR entityTokenCursor,\n+                                        ENTITY_CURSOR entityCursor,\n+                                        PropertyCursor propertyCursor,\n+                                        EntityFactory<T> entityFactory,\n+                                        IndexQuery[] queries)\n     {\n-        super( entityFactory );\n+        super(entityFactory);\n         this.entityTokenCursor = entityTokenCursor;\n         this.entityCursor = entityCursor;\n         this.propertyCursor = propertyCursor;\n@@ -56,13 +56,12 @@ public abstract class PropertyFilteringIterator<T extends Entity, TOKEN_CURSOR e\n         {\n             hasNext = entityTokenCursor.next();\n         }\n-        while ( hasNext && !hasPropertiesWithValues() );\n+        while (hasNext && !hasPropertiesWithValues());\n \n-        if ( hasNext )\n+        if (hasNext)\n         {\n-            return entityReference( entityTokenCursor );\n-        }\n-        else\n+            return entityReference(entityTokenCursor);\n+        } else\n         {\n             close();\n             return NO_ID;\n@@ -72,31 +71,30 @@ public abstract class PropertyFilteringIterator<T extends Entity, TOKEN_CURSOR e\n     @Override\n     void closeResources()\n     {\n-        IOUtils.closeAllSilently( entityTokenCursor, entityCursor, propertyCursor );\n+        IOUtils.closeAllSilently(entityTokenCursor, entityCursor, propertyCursor);\n     }\n \n     private boolean hasPropertiesWithValues()\n     {\n         int targetCount = queries.length;\n-        singleEntity( entityReference( entityTokenCursor ), entityCursor );\n-        if ( entityCursor.next() )\n+        singleEntity(entityReference(entityTokenCursor), entityCursor);\n+        if (entityCursor.next())\n         {\n-            properties( entityCursor, propertyCursor );\n-            while ( propertyCursor.next() )\n+            properties(entityCursor, propertyCursor);\n+            while (propertyCursor.next())\n             {\n-                for ( IndexQuery query : queries )\n+                for (IndexQuery query : queries)\n                 {\n-                    if ( propertyCursor.propertyKey() == query.propertyKeyId() )\n+                    if (propertyCursor.propertyKey() == query.propertyKeyId())\n                     {\n-                        if ( query.acceptsValueAt( propertyCursor ) )\n+                        if (query.acceptsValueAt(propertyCursor))\n                         {\n                             targetCount--;\n-                            if ( targetCount == 0 )\n+                            if (targetCount == 0)\n                             {\n                                 return true;\n                             }\n-                        }\n-                        else\n+                        } else\n                         {\n                             return false;\n                         }\n@@ -107,9 +105,9 @@ public abstract class PropertyFilteringIterator<T extends Entity, TOKEN_CURSOR e\n         return false;\n     }\n \n-    protected abstract long entityReference( TOKEN_CURSOR cursor );\n+    protected abstract long entityReference(TOKEN_CURSOR cursor);\n \n-    protected abstract void singleEntity( long id, ENTITY_CURSOR cursor );\n+    protected abstract void singleEntity(long id, ENTITY_CURSOR cursor);\n \n-    protected abstract void properties( ENTITY_CURSOR entityCursor, PropertyCursor propertyCursor );\n+    protected abstract void properties(ENTITY_CURSOR entityCursor, PropertyCursor propertyCursor);\n }\n",
            "diff_size": 26
        },
        {
            "tool": "naturalize",
            "errors": [
                {
                    "line": "1",
                    "severity": "error",
                    "message": "Missing, wrong or duplicated license header",
                    "source": "com.puppycrawl.tools.checkstyle.checks.regexp.RegexpSinglelineCheck"
                }
            ],
            "diff": "diff --git a/home/fernanda/mnt/fernanda/git-styler/styler/python/experiments/results/neo4j-neo4j/errored/1/1876/PropertyFilteringIterator.java b/home/fernanda/mnt/fernanda/git-styler/styler/python/experiments/results/neo4j-neo4j/naturalize/1876/PropertyFilteringIterator.java\nindex 4285f38603e..b490930a0c0 100644\n--- a/home/fernanda/mnt/fernanda/git-styler/styler/python/experiments/results/neo4j-neo4j/errored/1/1876/PropertyFilteringIterator.java\n+++ b/home/fernanda/mnt/fernanda/git-styler/styler/python/experiments/results/neo4j-neo4j/naturalize/1876/PropertyFilteringIterator.java\n@@ -17,7 +17,6 @@\n  * You should have received a copy of the GNU General Public License\n  * along with this program.  If not, see <http://www.gnu.org/licenses/>.\n  */\n-\n package org.neo4j.kernel.impl.coreapi.internal;\n \n import org.neo4j.graphdb.Entity;\n@@ -35,8 +34,7 @@ public abstract class PropertyFilteringIterator<T extends Entity, TOKEN_CURSOR e\n     private final PropertyCursor propertyCursor;\n     private final IndexQuery[] queries;\n \n-    protected PropertyFilteringIterator( TOKEN_CURSOR entityTokenCursor,\n-                                         ENTITY_CURSOR entityCursor,\n+    protected PropertyFilteringIterator( TOKEN_CURSOR entityTokenCursor, ENTITY_CURSOR entityCursor,\n                                          PropertyCursor propertyCursor,\n                                          EntityFactory<T> entityFactory,\n                                          IndexQuery[] queries )\n@@ -112,4 +110,4 @@ public abstract class PropertyFilteringIterator<T extends Entity, TOKEN_CURSOR e\n     protected abstract void singleEntity( long id, ENTITY_CURSOR cursor );\n \n     protected abstract void properties( ENTITY_CURSOR entityCursor, PropertyCursor propertyCursor );\n-}\n+}\n\\ No newline at end of file\n",
            "diff_size": 4
        },
        {
            "tool": "codebuff",
            "errors": null,
            "diff": null
        },
        {
            "tool": "styler_random",
            "errors": [
                {
                    "line": "1",
                    "severity": "error",
                    "message": "Missing, wrong or duplicated license header",
                    "source": "com.puppycrawl.tools.checkstyle.checks.regexp.RegexpSinglelineCheck"
                }
            ],
            "diff": "",
            "diff_size": 0
        },
        {
            "tool": "styler_three_grams",
            "errors": [
                {
                    "line": "1",
                    "severity": "error",
                    "message": "Missing, wrong or duplicated license header",
                    "source": "com.puppycrawl.tools.checkstyle.checks.regexp.RegexpSinglelineCheck"
                }
            ],
            "diff": "diff --git a/home/fernanda/mnt/fernanda/git-styler/styler/python/experiments/results/neo4j-neo4j/errored/1/1876/PropertyFilteringIterator.java b/home/fernanda/mnt/fernanda/git-styler/styler/python/experiments/results/neo4j-neo4j/styler_three_grams/1876/PropertyFilteringIterator.java\nindex 4285f38603e..9817897eee7 100644\n--- a/home/fernanda/mnt/fernanda/git-styler/styler/python/experiments/results/neo4j-neo4j/errored/1/1876/PropertyFilteringIterator.java\n+++ b/home/fernanda/mnt/fernanda/git-styler/styler/python/experiments/results/neo4j-neo4j/styler_three_grams/1876/PropertyFilteringIterator.java\n@@ -17,7 +17,6 @@\n  * You should have received a copy of the GNU General Public License\n  * along with this program.  If not, see <http://www.gnu.org/licenses/>.\n  */\n-\n package org.neo4j.kernel.impl.coreapi.internal;\n \n import org.neo4j.graphdb.Entity;\n",
            "diff_size": 1
        }
    ],
    "repaired_by": [],
    "not_repaired_by": [
        "styler",
        "intellij",
        "naturalize",
        "codebuff",
        "styler_random",
        "styler_three_grams"
    ]
}